taskprogressbar/__init__.py
taskprogressbar/taskprogressbar.py
taskprogressbar-1.2.dist-info/LICENSE
taskprogressbar-1.2.dist-info/METADATA
taskprogressbar-1.2.dist-info/WHEEL
taskprogressbar-1.2.dist-info/top_level.txt
taskprogressbar-1.2.dist-info/RECORD
