Metadata-Version: 2.1
Name: taskprogressbar
Version: 1.2
Summary: A package for displaying a multi-color task progress bar in Jupyter.
Home-page: http://github.com/nwen-cu/taskprogressbar
Author: N.Wen
Author-email: nwen@clemson.edu
License: MIT
Requires-Python: >=3.6
License-File: LICENSE
Requires-Dist: ipywidgets
